{"assets/doctor.png":["assets/doctor.png"],"assets/doctor_1.png":["assets/doctor_1.png"],"assets/doctor_3.png":["assets/doctor_3.png"],"assets/doctor_4.png":["assets/doctor_4.png"],"assets/doctor_face.jpg":["assets/doctor_face.jpg"],"assets/emergency.png":["assets/emergency.png"],"assets/health-articles.png":["assets/health-articles.png"],"assets/healthcare.png":["assets/healthcare.png"],"assets/heartbeat.png":["assets/heartbeat.png"],"assets/hospital.png":["assets/hospital.png"],"assets/ic_emergency.png":["assets/ic_emergency.png"],"assets/ic_home_health.png":["assets/ic_home_health.png"],"assets/images/profile/edit.png":["assets/images/profile/edit.png"],"assets/images/profile/help.png":["assets/images/profile/help.png"],"assets/images/profile/logout.png":["assets/images/profile/logout.png"],"assets/images/profile/notification.png":["assets/images/profile/notification.png"],"assets/images/profile/profile.png":["assets/images/profile/profile.png"],"assets/images/profile/setting.png":["assets/images/profile/setting.png"],"assets/logo.png":["assets/logo.png"],"assets/medical-tips.png":["assets/medical-tips.png"],"assets/news.png":["assets/news.png"],"assets/user.png":["assets/user.png"],"packages/cupertino_icons/assets/CupertinoIcons.ttf":["packages/cupertino_icons/assets/CupertinoIcons.ttf"],"packages/flutter_map/lib/assets/flutter_map_logo.png":["packages/flutter_map/lib/assets/flutter_map_logo.png"],"packages/fluttertoast/assets/toastify.css":["packages/fluttertoast/assets/toastify.css"],"packages/fluttertoast/assets/toastify.js":["packages/fluttertoast/assets/toastify.js"]}